dynamic_storages/__init__.py
dynamic_storages/admin.py
dynamic_storages/apps.py
dynamic_storages/conf.py
dynamic_storages/fields/__init__.py
dynamic_storages/fields/dynamic_storage.py
dynamic_storages/fields/encrypted_content.py
dynamic_storages/fields/encrypted_json.py
dynamic_storages/migrations/__init__.py
dynamic_storages/models/__init__.py
dynamic_storages/models/abstract_storage_target.py
dynamic_storages/models/mappings.py
dynamic_storages/serializers.py
dynamic_storages/tasks/__init__.py
dynamic_storages/tests/__init__.py
dynamic_storages/tests/abstract.py
dynamic_storages/tests/data/files/1
dynamic_storages/tests/data/files/2
dynamic_storages/tests/data/files/3
dynamic_storages/tests/data/files/4
dynamic_storages/tests/data/files/5
dynamic_storages/tests/data/images/casey-horner-O6yAB2AZL8c-unsplash.jpg
dynamic_storages/tests/data/images/igorthegoodboy-on-ig-boston-terrier-G_7WU5AFBvQ-unsplash.jpg
dynamic_storages/tests/data/images/igorthegoodboy-on-ig-boston-terrier-H5quY5v1fLQ-unsplash.jpg
dynamic_storages/tests/data/images/karsten-winegeart-Y0nU6dqDCbY-unsplash.jpg
dynamic_storages/tests/data/images/meghan-schiereck-AEwgScCmbH0-unsplash.jpg
dynamic_storages/tests/data/sftp/sftp-test
dynamic_storages/tests/data/sftp/sftp-test-passphrase
dynamic_storages/tests/data/sftp/sftp-test-passphrase.pub
dynamic_storages/tests/data/sftp/sftp-test.pub
dynamic_storages/tests/factories.py
dynamic_storages/tests/fields/__init__.py
dynamic_storages/tests/fields/test_dynamic_storage_fields.py
dynamic_storages/tests/fields/test_encrypted_fields.py
dynamic_storages/tests/fields/test_encrypted_json_field.py
dynamic_storages/tests/fields/util.py
dynamic_storages/tests/migrations/0001_initial.py
dynamic_storages/tests/migrations/0002_testencryptedjsonfield.py
dynamic_storages/tests/migrations/0003_auto_20201121_0302.py
dynamic_storages/tests/migrations/__init__.py
dynamic_storages/tests/models.py
dynamic_storages/tests/test_factories.py
dynamic_storages/tests/urls.py
django_dynamic_storages-0.5.3.dist-info/LICENSE
django_dynamic_storages-0.5.3.dist-info/WHEEL
django_dynamic_storages-0.5.3.dist-info/METADATA
django_dynamic_storages-0.5.3.dist-info/RECORD
